email_send_mcp/__init__.py
email_send_mcp/__main__.py
email_send_mcp/client.py
email_send_mcp/email.json
email_send_mcp/server.py
email_send_mcp/server_fastmcp.py
email_send_mcp-0.1.2.dist-info/licenses/LICENSE
email_send_mcp-0.1.2.dist-info/METADATA
email_send_mcp-0.1.2.dist-info/WHEEL
email_send_mcp-0.1.2.dist-info/entry_points.txt
email_send_mcp-0.1.2.dist-info/top_level.txt
email_send_mcp-0.1.2.dist-info/RECORD
