Metadata-Version: 2.4
Name: email-send-mcp
Version: 0.1.2
Summary: A Model Context Protocol server that provides email functionality
Author-email: Yu Hai <me.yuhai@hotmail.com>
License-Expression: MIT
Keywords: email,mcp,model-context-protocol,smtp
Classifier: Development Status :: 3 - Alpha
Classifier: Intended Audience :: Developers
Classifier: Programming Language :: Python :: 3
Classifier: Programming Language :: Python :: 3.10
Classifier: Programming Language :: Python :: 3.11
Classifier: Programming Language :: Python :: 3.12
Classifier: Topic :: Communications :: Email
Classifier: Topic :: Software Development :: Libraries :: Python Modules
Requires-Python: >=3.10
License-File: LICENSE
Requires-Dist: mcp>=1.0.0
Requires-Dist: pydantic<3.0.0,>=2.0.0
Requires-Dist: python-dotenv<2.0.0,>=0.19.0
Requires-Dist: anthropic<1.0.0,>=0.3.0
Dynamic: license-file
